[
  {
    "id": "5200301",
    "sort_order": "1",
    "title_text": "Lovely Hot Spring",
    "summary_text": "Kazuma, Aqua, and Darkness stopped by a hot spring.",
    "gacha_id": "320031",
    "banner_group": "5200301",
    "list_icon_type": "member",
    "list_icon_id": "1014107",
    "start_load_voice_id": "302101002",
    "end_load_voice_id": "302103003",
    "banner": "banner_gacha_320031.png",
    "scriptPath": "5200301.txt"
  },
  {
    "id": "5200302",
    "sort_order": "1",
    "title_text": "Last Snow Day of Winter",
    "summary_text": "Dust and Rin arrived at the slopes for some cold-weather fun. Unbeknownst to Rin, her friend had something important to tell her.",
    "gacha_id": "320032",
    "banner_group": "5200302",
    "list_icon_type": "member",
    "list_icon_id": "1124110",
    "start_load_voice_id": "302112002",
    "end_load_voice_id": "302113003",
    "banner": "banner_gacha_320032.png",
    "scriptPath": "5200302.txt"
  },
  {
    "id": "5200401",
    "sort_order": "1",
    "title_text": "Super Fun! Pajama Party",
    "summary_text": "Megumin, Wiz, and Yunyun changed into their pajamas for a girl's night in. Yunyun could barely contain her excitement, but...",
    "gacha_id": "320041",
    "banner_group": "5200401",
    "list_icon_type": "member",
    "list_icon_id": "1024113",
    "start_load_voice_id": "302105002",
    "end_load_voice_id": "302102002",
    "banner": "banner_gacha_320041.png",
    "scriptPath": "5200401.txt"
  },
  {
    "id": "5200402",
    "sort_order": "1",
    "title_text": "Glamorous Casino Bunny",
    "summary_text": "Cecily entered the casino to do some missionary work. At Aqua's request, Mitsurugi joined the efforts, causing Cecily to get a little off track...",
    "gacha_id": "320042",
    "banner_group": "5200402",
    "list_icon_type": "member",
    "list_icon_id": "1094114",
    "start_load_voice_id": "302109002",
    "end_load_voice_id": "302111003",
    "banner": "banner_gacha_320042.png",
    "scriptPath": "5200402.txt"
  },
  {
    "id": "5200403",
    "sort_order": "1",
    "title_text": "Glamorous Casino Bunny",
    "summary_text": "Due to her lack of real-world experience, Iris expressed a desire to go places she'd never been. Chris decided to take her to a casino...",
    "gacha_id": "320043",
    "banner_group": "5200403",
    "list_icon_type": "member",
    "list_icon_id": "1074114",
    "start_load_voice_id": "302107002",
    "end_load_voice_id": "302104002",
    "banner": "banner_gacha_320043.png",
    "scriptPath": "5200403.txt"
  },
  {
    "id": "5200501",
    "sort_order": "1",
    "title_text": "Roleplaying! Heroic Party",
    "summary_text": "As Kazuma and company continued practicing for the big show, his passion as the hero of the story surged! A star was about to be born!",
    "gacha_id": "320051",
    "banner_group": "5200501",
    "list_icon_type": "member",
    "list_icon_id": "1104116",
    "start_load_voice_id": "302100002",
    "end_load_voice_id": "302110002",
    "banner": "banner_gacha_320051.png",
    "scriptPath": "5200501.txt"
  },
  {
    "id": "5200502",
    "sort_order": "1",
    "title_text": "Manic Mansion! Maid",
    "summary_text": "Amy and Mia took jobs as maids at a nobleman's mansion, but Mia's innocent recklessness might not be a good fit for the job...",
    "gacha_id": "320052",
    "banner_group": "5200502",
    "list_icon_type": "member",
    "list_icon_id": "1184117",
    "start_load_voice_id": "302118002",
    "end_load_voice_id": "302119002",
    "banner": "banner_gacha_320052.png",
    "scriptPath": "5200502.txt"
  },
  {
    "id": "5200503",
    "sort_order": "1",
    "title_text": "Manic Mansion! Maid",
    "summary_text": "Chris and Melissa coincidentally found work as maids in the same mansion. However, they both took the job with ulterior motives...",
    "gacha_id": "320053",
    "banner_group": "5200503",
    "list_icon_type": "member",
    "list_icon_id": "1044117",
    "start_load_voice_id": "302104002",
    "end_load_voice_id": "302117002",
    "banner": "banner_gacha_320053.png",
    "scriptPath": "5200503.txt"
  },
  {
    "id": "5200601",
    "sort_order": "1",
    "title_text": "Crimson Magic Academy",
    "summary_text": "Yunyun visited the Crimson Magic Academy with Megumin. Amidst all the memories, Yunyun gave something to her cherished friend...",
    "gacha_id": "320061",
    "banner_group": "5200601",
    "list_icon_type": "member",
    "list_icon_id": "1024118",
    "start_load_voice_id": "302102002",
    "end_load_voice_id": "302106002",
    "banner": "banner_gacha_320061.png",
    "scriptPath": "5200601.txt"
  },
  {
    "id": "5200602",
    "sort_order": "1",
    "title_text": "Shining Future! Axel Hearts",
    "summary_text": "Cielo and Erika were practicing their dancing until Erika uttered a certain word that lit a fire under Cielo...",
    "gacha_id": "320062",
    "banner_group": "5200602",
    "list_icon_type": "member",
    "list_icon_id": "1154105",
    "start_load_voice_id": "302115002",
    "end_load_voice_id": "302116002",
    "banner": "banner_gacha_320062.png",
    "scriptPath": "5200602.txt"
  },
  {
    "id": "5200603",
    "sort_order": "1",
    "title_text": "Shining Future! Axel Hearts",
    "summary_text": "Lia forgot she was supposed to go on a quest with Kazuma's party. When he came to get her, she was still looking for the proper attire...",
    "gacha_id": "320063",
    "banner_group": "5200603",
    "list_icon_type": "member",
    "list_icon_id": "1144105",
    "start_load_voice_id": "302114002",
    "end_load_voice_id": "302114003",
    "banner": "banner_gacha_320063.png",
    "scriptPath": "5200603.txt"
  },
  {
    "id": "5200701",
    "sort_order": "1",
    "title_text": "Shall We Dance?",
    "summary_text": "In the hall filled with exquisite food and bubbly, who would Iris choose as her dance partner?",
    "gacha_id": "320071",
    "banner_group": "5200701",
    "list_icon_type": "member",
    "list_icon_id": "1074119",
    "start_load_voice_id": "302107002",
    "end_load_voice_id": "302100002",
    "banner": "banner_gacha_320071.png",
    "scriptPath": "5200701.txt"
  },
  {
    "id": "5200702",
    "sort_order": "1",
    "title_text": "Sparkling Summer! Swimsuit",
    "summary_text": "Rin admires Melissa's calm and composed style, but a sudden encounter revealed an unexpected side to her cool demeanor...",
    "gacha_id": "320072",
    "banner_group": "5200702",
    "list_icon_type": "member",
    "list_icon_id": "1174123",
    "start_load_voice_id": "302113002",
    "end_load_voice_id": "302117002",
    "banner": "banner_gacha_320072.png",
    "scriptPath": "5200702.txt"
  },
  {
    "id": "5200703",
    "sort_order": "1",
    "title_text": "Sparkling Summer! Swimsuit",
    "summary_text": "Summer is a time for beaches and swimsuits! Darkness ran into a familiar face while shopping for a new swimsuit...",
    "gacha_id": "320073",
    "banner_group": "5200703",
    "list_icon_type": "member",
    "list_icon_id": "1034123",
    "start_load_voice_id": "302103002",
    "end_load_voice_id": "302106002",
    "banner": "banner_gacha_320073.png",
    "scriptPath": "5200703.txt"
  },
  {
    "id": "5200801",
    "sort_order": "1",
    "title_text": "Exciting Swimsuit Adventure!",
    "summary_text": "Aqua, Megumin, and Wiz went shopping for swimsuits. However, a comment from Wiz led to a change in mood for the group...",
    "gacha_id": "320081",
    "banner_group": "5200801",
    "list_icon_type": "member",
    "list_icon_id": "1014123",
    "start_load_voice_id": "302101002",
    "end_load_voice_id": "302105002",
    "banner": "banner_gacha_320081.png",
    "scriptPath": "5200801.txt"
  },
  {
    "id": "5200802",
    "sort_order": "1",
    "title_text": "Starry Arabian Nights",
    "summary_text": "Chris and Dust snuck into a vault in search of treasure. This unlikely pair was in search of the same thing: a magic lamp...",
    "gacha_id": "320082",
    "banner_group": "5200802",
    "list_icon_type": "member",
    "list_icon_id": "1044125",
    "start_load_voice_id": "302104002",
    "end_load_voice_id": "302112003",
    "banner": "banner_gacha_320082.png",
    "scriptPath": "5200802.txt"
  },
  {
    "id": "5200803",
    "sort_order": "1",
    "title_text": "Starry Arabian Nights",
    "summary_text": "Amy agrees to participate in a desert festival. To spice things up, she teams with Cielo to form a special dance team.",
    "gacha_id": "320083",
    "banner_group": "5200803",
    "list_icon_type": "member",
    "list_icon_id": "1194125",
    "start_load_voice_id": "302115002",
    "end_load_voice_id": "302119002",
    "banner": "banner_gacha_320083.png",
    "scriptPath": "5200803.txt"
  },
  {
    "id": "5200901",
    "sort_order": "1",
    "title_text": "Beautiful Waitress",
    "summary_text": "Megumin tries on her waitress uniform to help out at the cafe. For some reason, a strange glint appears in Cecily's eyes...",
    "gacha_id": "410020",
    "banner_group": "5200901",
    "list_icon_type": "member",
    "list_icon_id": "1024126",
    "start_load_voice_id": "302102002",
    "end_load_voice_id": "302109002",
    "banner": "banner_gacha_320091.png",
    "scriptPath": "5200901.txt"
  },
  {
    "id": "5200902",
    "sort_order": "1",
    "title_text": "Ninja Transformation",
    "summary_text": "Mia has a new hobby: playing ninja. Despite Mitsurugi's bewilderment, Mia looks to show off her newfound moves!",
    "gacha_id": "320092",
    "banner_group": "5200902",
    "list_icon_type": "member",
    "list_icon_id": "1184127",
    "start_load_voice_id": "302111002",
    "end_load_voice_id": "302118002",
    "banner": "banner_gacha_320092.png",
    "scriptPath": "5200902.txt"
  },
  {
    "id": "5200903",
    "sort_order": "1",
    "title_text": "Ninja Transformation",
    "summary_text": "Kunoichi are female ninja that slay their enemies from the shadows! Their activities include assassination, spying, and breaking hearts!",
    "gacha_id": "320093",
    "banner_group": "5200903",
    "list_icon_type": "member",
    "list_icon_id": "1104127",
    "start_load_voice_id": "302105002",
    "end_load_voice_id": "302110003",
    "banner": "banner_gacha_320093.png",
    "scriptPath": "5200903.txt"
  },
  {
    "id": "5201001",
    "sort_order": "1",
    "title_text": "Adorable Trick-or-Treat",
    "summary_text": "Aqua teaches Yunyun and Iris about Halloween as the town prepares to celebrate the lively festival.",
    "gacha_id": "320101",
    "banner_group": "5201001",
    "list_icon_type": "member",
    "list_icon_id": "1074129",
    "start_load_voice_id": "302106002",
    "end_load_voice_id": "302107003",
    "banner": "banner_gacha_320101.png",
    "scriptPath": "5201001.txt"
  },
  {
    "id": "5201002",
    "sort_order": "1",
    "title_text": "Mighty Martial Arts Girls",
    "summary_text": "Lia and Melissa take up martial arts to further enhance their beauty. During their training, Melissa teaches Lia what it takes to be a good woman.",
    "gacha_id": "320102",
    "banner_group": "5201002",
    "list_icon_type": "member",
    "list_icon_id": "1144130",
    "start_load_voice_id": "302114002",
    "end_load_voice_id": "302117002",
    "banner": "banner_gacha_320102.png",
    "scriptPath": "5201002.txt"
  },
  {
    "id": "5201003",
    "sort_order": "1",
    "title_text": "Mighty Martial Arts Girls",
    "summary_text": "Erika and Cecily use martial arts to improve their appearance. Erika is delighted at her cute outfit, while Cecily has other priorities...",
    "gacha_id": "320103",
    "banner_group": "5201003",
    "list_icon_type": "member",
    "list_icon_id": "1164130",
    "start_load_voice_id": "302116003",
    "end_load_voice_id": "302109003",
    "banner": "banner_gacha_320103.png",
    "scriptPath": "5201003.txt"
  },
  {
    "id": "5201101",
    "sort_order": "1",
    "title_text": "Re:ZERO Collaboration",
    "summary_text": "Aqua shows off the outfits she made for Emilia and Rem. Along with Megumin, they try them on, although Megumin's fit is a bit loose...",
    "gacha_id": "320111",
    "banner_group": "5201101",
    "list_icon_type": "member",
    "list_icon_id": "1504132",
    "start_load_voice_id": "302101002",
    "end_load_voice_id": "302150002",
    "banner": "banner_gacha_320111.png",
    "scriptPath": "5201101.txt"
  },
  {
    "id": "5201102",
    "sort_order": "1",
    "title_text": "Manic Mansion! Maid",
    "summary_text": "Rin and Cielo attempt to become maids. The work is hard, but they each have their own reasons for making the effort.",
    "gacha_id": "320112",
    "banner_group": "5201102",
    "list_icon_type": "member",
    "list_icon_id": "1134117",
    "start_load_voice_id": "302113002",
    "end_load_voice_id": "302115002",
    "banner": "banner_gacha_320112.png",
    "scriptPath": "5201102.txt"
  },
  {
    "id": "5201103",
    "sort_order": "1",
    "title_text": "Ninja Transformation",
    "summary_text": "Dressed in ninja garb, Kazuma and Lia were attempting to make off with a trove of monster-guarded treasure. Amazed by the custom-made ninja gear, Lia accidentally activated an enchanted light scroll...",
    "gacha_id": "320113",
    "banner_group": "5201103",
    "list_icon_type": "member",
    "list_icon_id": "1004127",
    "start_load_voice_id": "302114002",
    "end_load_voice_id": "302100002",
    "banner": "banner_gacha_320113.png",
    "scriptPath": "5201103.txt"
  },
  {
    "id": "5201201",
    "sort_order": "1",
    "title_text": "Setting Up for Santa",
    "summary_text": "Darkness, Iris, and Wiz were busily preparing for the party. As they worked, the more that \"Santa\" fellow Kazuma mentioned loomed large...",
    "gacha_id": "320121",
    "banner_group": "5201201",
    "list_icon_type": "member",
    "list_icon_id": "1034135",
    "start_load_voice_id": "302103002",
    "end_load_voice_id": "302105002",
    "banner": "banner_gacha_320121.png",
    "scriptPath": "5201201.txt"
  },
  {
    "id": "5201202",
    "sort_order": "1",
    "title_text": "Lovely Hot Spring",
    "summary_text": "Yunyun arrives at a long-sought destination, an Arcanretian hot spring Megumin was raving about—where a familiar voice greets her.",
    "gacha_id": "320122",
    "banner_group": "5201202",
    "list_icon_type": "member",
    "list_icon_id": "1064107",
    "start_load_voice_id": "302106002",
    "end_load_voice_id": "302112002",
    "banner": "banner_gacha_320122.png",
    "scriptPath": "5201202.txt"
  },
  {
    "id": "5201203",
    "sort_order": "1",
    "title_text": "Winter Wonderland! Snowfall",
    "summary_text": "Having heard of the exotic custom of \"ice skating\" from Kazuma, Chris and Erika give it a whirl. Catching on quickly, Chris shows Erika the ropes with an almost royal grace.",
    "gacha_id": "320123",
    "banner_group": "5201203",
    "list_icon_type": "member",
    "list_icon_id": "1044110",
    "start_load_voice_id": "302116003",
    "end_load_voice_id": "302104003",
    "banner": "banner_gacha_320123.png",
    "scriptPath": "5201203.txt"
  },
  {
    "id": "5210101",
    "sort_order": "1",
    "title_text": "Blossoming New Year's Furisode",
    "summary_text": "Ever the talented tailor, Aqua produces an entire furisode wardrobe for the gang. They eagerly prepare for a New Year's like never before.",
    "gacha_id": "321011",
    "banner_group": "5210101",
    "list_icon_type": "member",
    "list_icon_id": "1014137",
    "start_load_voice_id": "302101002",
    "end_load_voice_id": "302102002",
    "banner": "banner_gacha_321011.png",
    "scriptPath": "5210101.txt"
  },
  {
    "id": "5210102",
    "sort_order": "1",
    "title_text": "Winter Wonderland! Snowfall",
    "summary_text": "The new year sees an abundance of street vendors lining Axel's roads. It is there Mitsurugi runs into Arue, who delivers an ominous message to the knight...",
    "gacha_id": "321012",
    "banner_group": "5210102",
    "list_icon_type": "member",
    "list_icon_id": "1104110",
    "start_load_voice_id": "302111002",
    "end_load_voice_id": "302110002",
    "banner": "banner_gacha_321012.png",
    "scriptPath": "5210102.txt"
  },
  {
    "id": "5210103",
    "sort_order": "1",
    "title_text": "Dreamy Pajama Night",
    "summary_text": "Erika comes across Amy, immersed in her pre-bedtime skincare routine. Hoping to reach new heights of cuteness, the idol begins to learn from the expert.",
    "gacha_id": "321013",
    "banner_group": "5210103",
    "list_icon_type": "member",
    "list_icon_id": "1194113",
    "start_load_voice_id": "302116002",
    "end_load_voice_id": "302119003",
    "banner": "banner_gacha_321013.png",
    "scriptPath": "5210103.txt"
  },
  {
    "id": "5210201",
    "sort_order": "1",
    "title_text": "Heartfelt Valentine",
    "summary_text": "Iris practices making sweets under Lia's tutelage. Moved by the princess's determination, Cecily chimes in with some unique advice.",
    "gacha_id": "321021",
    "banner_group": "5210201",
    "list_icon_type": "member",
    "list_icon_id": "1074139",
    "start_load_voice_id": "302107002",
    "end_load_voice_id": "302109003",
    "banner": "banner_gacha_321021.png",
    "scriptPath": "5210201.txt"
  },
  {
    "id": "5210202",
    "sort_order": "1",
    "title_text": "Dreamy Pajama Night",
    "summary_text": "Amy asks Cielo to look after Mia for a night. The two pass the time with some stimulating girls talk.",
    "gacha_id": "321022",
    "banner_group": "5210202",
    "list_icon_type": "member",
    "list_icon_id": "1154113",
    "start_load_voice_id": "302118003",
    "end_load_voice_id": "302115002",
    "banner": "banner_gacha_321022.png",
    "scriptPath": "5210202.txt"
  },
  {
    "id": "5210203",
    "sort_order": "1",
    "title_text": "Lovely Hot Spring",
    "summary_text": "Melissa visits Arcanretia's hot springs to get away from it all, but finds a familiar face awaiting her there...",
    "gacha_id": "321023",
    "banner_group": "5210203",
    "list_icon_type": "member",
    "list_icon_id": "1174107",
    "start_load_voice_id": "302117002",
    "end_load_voice_id": "302110002",
    "banner": "banner_gacha_321023.png",
    "scriptPath": "5210203.txt"
  },
  {
    "id": "5210301",
    "sort_order": "1",
    "title_text": "Axel Singing Contest",
    "summary_text": "The singing duo of Kazuma and Megumin share ideas for a grand self-introduction during their contest entrance.",
    "gacha_id": "321031",
    "banner_group": "5210301",
    "list_icon_type": "member",
    "list_icon_id": "1024141",
    "start_load_voice_id": "302102002",
    "end_load_voice_id": "302100002",
    "banner": "banner_gacha_321034.png",
    "scriptPath": "5210301.txt"
  },
  {
    "id": "5210302",
    "sort_order": "1",
    "title_text": "Komekko Joins the Battle! Devilish Little Sister",
    "summary_text": "Komekko is hunting a pack of giant toads. When she finally finds them, she lets Hoost do all the work in taking them down.",
    "gacha_id": "321032",
    "banner_group": "5210302",
    "list_icon_type": "member",
    "list_icon_id": "1084100",
    "start_load_voice_id": "302108002",
    "end_load_voice_id": "302108003",
    "banner": "banner_gacha_321032.png",
    "scriptPath": "5210302.txt"
  },
  {
    "id": "5210303",
    "sort_order": "1",
    "title_text": "Mighty Martial Arts Girls",
    "summary_text": "Wiz and Mia dress up in martial arts gear to help promote Wiz's shop. Mia is certain she can attract customers, but...",
    "gacha_id": "321033",
    "banner_group": "5210303",
    "list_icon_type": "member",
    "list_icon_id": "1054130",
    "start_load_voice_id": "302105002",
    "end_load_voice_id": "302118002",
    "banner": "banner_gacha_321033.png",
    "scriptPath": "5210303.txt"
  },
  {
    "id": "5210401",
    "sort_order": "1",
    "title_text": "Youthful School Life",
    "summary_text": "Yunyun and Erika give in to Kazuma's request and put on the school uniforms, which they find to be surprisingly cute.",
    "gacha_id": "321041",
    "banner_group": "5210401",
    "list_icon_type": "member",
    "list_icon_id": "1064144",
    "start_load_voice_id": "302116003",
    "end_load_voice_id": "302106002",
    "banner": "banner_gacha_321041.png",
    "scriptPath": "5210401.txt"
  },
  {
    "id": "5210402",
    "sort_order": "1",
    "title_text": "Youthful School Life",
    "summary_text": "Dust visits Lia while wearing a school uniform, and tries to get her to take his jacket's second button. What is he up to?",
    "gacha_id": "321042",
    "banner_group": "5210402",
    "list_icon_type": "member",
    "list_icon_id": "1144144",
    "start_load_voice_id": "302112002",
    "end_load_voice_id": "302114002",
    "banner": "banner_gacha_321042.png",
    "scriptPath": "5210402.txt"
  },
  {
    "id": "5210403",
    "sort_order": "1",
    "title_text": "Ninja Transformation",
    "summary_text": "Amy insists that Chris should teach her how to be a proper ninja...but why?",
    "gacha_id": "321043",
    "banner_group": "5210403",
    "list_icon_type": "member",
    "list_icon_id": "1044127",
    "start_load_voice_id": "302104002",
    "end_load_voice_id": "302119002",
    "banner": "banner_gacha_321043.png",
    "scriptPath": "5210403.txt"
  },
  {
    "id": "5210501",
    "sort_order": "1",
    "title_text": "DanMachi III Collaboration",
    "summary_text": "Aqua shows off her Hestia outfit to Bell, but Hestia is none too impressed. Just then, Ais and Darkness arrive wearing the same thing too...",
    "gacha_id": "321051",
    "banner_group": "5210501",
    "list_icon_type": "member",
    "list_icon_id": "1604147",
    "start_load_voice_id": "302160002",
    "end_load_voice_id": "302103002",
    "banner": "banner_gacha_321051.png",
    "scriptPath": "5210501.txt"
  },
  {
    "id": "5210502",
    "sort_order": "1",
    "title_text": "Ninja Transformation",
    "summary_text": "The darkness of night is a ninja's friend. Black-clad Cecily takes Rin on a clandestine mission to deliver Order of Axis flyers.",
    "gacha_id": "321052",
    "banner_group": "5210502",
    "list_icon_type": "member",
    "list_icon_id": "1094127",
    "start_load_voice_id": "302109002",
    "end_load_voice_id": "302113003",
    "banner": "banner_gacha_321052.png",
    "scriptPath": "5210502.txt"
  },
  {
    "id": "5210503",
    "sort_order": "1",
    "title_text": "Dreamy Pajama Night",
    "summary_text": "Arue kindly agrees to join Komekko, who wants to stay up past her bedtime. That is, until Komekko suddenly nods off...",
    "gacha_id": "321053",
    "banner_group": "5210503",
    "list_icon_type": "member",
    "list_icon_id": "1084113",
    "start_load_voice_id": "302108002",
    "end_load_voice_id": "302110002",
    "banner": "banner_gacha_321053.png",
    "scriptPath": "5210503.txt"
  },
  {
    "id": "5210601",
    "sort_order": "1",
    "title_text": "Snow Country Festival",
    "summary_text": "Mia and Amy are trying on festival outfits. Mia is excited for the upcoming festivities, but Amy has her doubts.",
    "gacha_id": "321061",
    "banner_group": "5210601",
    "list_icon_type": "member",
    "list_icon_id": "1184149",
    "start_load_voice_id": "302118002",
    "end_load_voice_id": "302119003",
    "banner": "banner_gacha_321064.png",
    "scriptPath": "5210601.txt"
  },
  {
    "id": "5210602",
    "sort_order": "1",
    "title_text": "Starry Arabian Nights",
    "summary_text": "Mitsurugi offers to join Melissa on one of her treasure hunts. Just before entering the ruins, Melissa senses Mitsurugi's eyes on her...",
    "gacha_id": "321062",
    "banner_group": "5210602",
    "list_icon_type": "member",
    "list_icon_id": "1174125",
    "start_load_voice_id": "302111002",
    "end_load_voice_id": "302117002",
    "banner": "banner_gacha_321062.png",
    "scriptPath": "5210602.txt"
  },
  {
    "id": "5210603",
    "sort_order": "1",
    "title_text": "Glamorous Casino Bunny",
    "summary_text": "Dust is once again busy losing everything at the casino, when he spots Wiz working the casino floor, wearing a strange outfit...",
    "gacha_id": "321063",
    "banner_group": "5210603",
    "list_icon_type": "member",
    "list_icon_id": "1054114",
    "start_load_voice_id": "302112002",
    "end_load_voice_id": "302105002",
    "banner": "banner_gacha_321063.png",
    "scriptPath": "5210603.txt"
  },
  {
    "id": "5210701",
    "sort_order": "1",
    "title_text": "Making Summer Memories",
    "summary_text": "Arue is penning her novel at the beach. Iris is fascinated with her grand tale of adventure, and is eager to hear how it ends...",
    "gacha_id": "321071",
    "banner_group": "5210701",
    "list_icon_type": "member",
    "list_icon_id": "1074151",
    "start_load_voice_id": "302107002",
    "end_load_voice_id": "302110002",
    "banner": "banner_gacha_321071.png",
    "scriptPath": "5210701.txt"
  },
  {
    "id": "5210702",
    "sort_order": "1",
    "title_text": "Making Summer Memories",
    "summary_text": "Erika invites Cielo to go swimming in the sea, but Cielo is not confident in the water, so Erika offers to teach her how to swim.",
    "gacha_id": "321072",
    "banner_group": "5210702",
    "list_icon_type": "member",
    "list_icon_id": "1154151",
    "start_load_voice_id": "302116002",
    "end_load_voice_id": "302115002",
    "banner": "banner_gacha_321072.png",
    "scriptPath": "5210702.txt"
  },
  {
    "id": "5210703",
    "sort_order": "1",
    "title_text": "Making Summer Memories",
    "summary_text": "Chris and Mitsurugi are helping out at the grilled squid stall, but are starting to reconsider the division of labor with their so-called boss, Kazuma...",
    "gacha_id": "321073",
    "banner_group": "5210703",
    "list_icon_type": "member",
    "list_icon_id": "1044151",
    "start_load_voice_id": "302111002",
    "end_load_voice_id": "302104003",
    "banner": "banner_gacha_321073.png",
    "scriptPath": "5210703.txt"
  },
  {
    "id": "5210801",
    "sort_order": "1",
    "title_text": "Fireworks at the Yukata Festival",
    "summary_text": "Yunyun and Komekko have a goldfish-catching contest while at the festival, but Komekko takes things a little too seriously...",
    "gacha_id": "321081",
    "banner_group": "5210801",
    "list_icon_type": "member",
    "list_icon_id": "1064154",
    "start_load_voice_id": "302108003",
    "end_load_voice_id": "302106002",
    "banner": "banner_gacha_321081.png",
    "scriptPath": "5210801.txt"
  },
  {
    "id": "5210802",
    "sort_order": "1",
    "title_text": "Mel Joins the Battle! Lightning Girl",
    "summary_text": "The quest was a success, and although the group is growing tired of Mel's pranks, she is just getting started!",
    "gacha_id": "321082",
    "banner_group": "5210802",
    "list_icon_type": "member",
    "list_icon_id": "1514100",
    "start_load_voice_id": "302151002",
    "end_load_voice_id": "302151003",
    "banner": "banner_gacha_321082.png",
    "scriptPath": "5210802.txt"
  },
  {
    "id": "5210803",
    "sort_order": "1",
    "title_text": "Fireworks at the Yukata Festival",
    "summary_text": "Rin and Amy attend the Crimson Demons' summer festival. While dressed in yukatas, they peruse the somewhat outlandish fare of the food stalls.",
    "gacha_id": "321083",
    "banner_group": "5210803",
    "list_icon_type": "member",
    "list_icon_id": "1194154",
    "start_load_voice_id": "302119002",
    "end_load_voice_id": "302113002",
    "banner": "banner_gacha_321083.png",
    "scriptPath": "5210803.txt"
  },
  {
    "id": "5210901",
    "sort_order": "1",
    "title_text": "Vanir Joins the Battle! Masked Demon",
    "summary_text": "Vanir breaks with convention and joins Kazuma's group on a quest. Kazuma admires Vanir's battle skill and makes him an offer.",
    "gacha_id": "321091",
    "banner_group": "5210901",
    "list_icon_type": "member",
    "list_icon_id": "1284100",
    "start_load_voice_id": "302128002",
    "end_load_voice_id": "302128003",
    "banner": "banner_gacha_321091.png",
    "scriptPath": "5210901.txt"
  },
  {
    "id": "5210902",
    "sort_order": "1",
    "title_text": "Manic Mansion! Maid",
    "summary_text": "Kazuma and Lia are working at Darkness's family estate when Kazuma does something unexpected to an embarrassed Lalatina.",
    "gacha_id": "321092",
    "banner_group": "5210902",
    "list_icon_type": "member",
    "list_icon_id": "1144117",
    "start_load_voice_id": "302114002",
    "end_load_voice_id": "302100002",
    "banner": "banner_gacha_321092.png",
    "scriptPath": "5210902.txt"
  },
  {
    "id": "5210903",
    "sort_order": "1",
    "title_text": "Hear My Voice! Showtime",
    "summary_text": "Mel was excitedly getting ready to perform another show with Axel hearts. On the other hand, Squall was doing his best to prepare for the inevitable antics of his mischief-loving roommate.",
    "gacha_id": "321093",
    "banner_group": "5210903",
    "list_icon_type": "member",
    "list_icon_id": "1514105",
    "start_load_voice_id": "302151002",
    "end_load_voice_id": "302151003",
    "banner": "banner_gacha_321093.png",
    "scriptPath": "5210903.txt"
  },
  {
    "id": "5211001",
    "sort_order": "1",
    "title_text": "Spooky Trick-or-Treat",
    "summary_text": "The town residents must have liked their costumes, because Aqua and Mia were having no trouble rounding up candy on Halloween. Mia wished wistfully that every day was Halloween, but...",
    "gacha_id": "321101",
    "banner_group": "5211001",
    "list_icon_type": "member",
    "list_icon_id": "1014160",
    "start_load_voice_id": "302118002",
    "end_load_voice_id": "302101002",
    "banner": "banner_gacha_321101.png",
    "scriptPath": "5211001.txt"
  },
  {
    "id": "5211002",
    "sort_order": "1",
    "title_text": "Spooky Trick-or-Treat",
    "summary_text": "Erika was struggling to write lyrics for her Halloween song, when suddenly, she hears Komekko singing and can't believe her ears!",
    "gacha_id": "321102",
    "banner_group": "5211002",
    "list_icon_type": "member",
    "list_icon_id": "1084160",
    "start_load_voice_id": "302116002",
    "end_load_voice_id": "302108002",
    "banner": "banner_gacha_321102.png",
    "scriptPath": "5211002.txt"
  },
  {
    "id": "5211003",
    "sort_order": "1",
    "title_text": "Dreamy Pajama Night",
    "summary_text": "Melissa was fawning all over Dust, who feigns indifference. He was excited for what looked to be the beginning of a long night, until reality set in...",
    "gacha_id": "321103",
    "banner_group": "5211003",
    "list_icon_type": "member",
    "list_icon_id": "1174113",
    "start_load_voice_id": "302112002",
    "end_load_voice_id": "302117002",
    "banner": "banner_gacha_321103.png",
    "scriptPath": "5211003.txt"
  },
  {
    "id": "5211101",
    "sort_order": "1",
    "title_text": "OVERLORD Collaboration P1",
    "summary_text": "Aqua made Kazuma and Darkness costumes in Ainz and Albedo's likenesses. Darkness is rather embarrassed as well as, in typical Darkness-fashion, excited at wearing the revealing outfit.",
    "gacha_id": "321111",
    "banner_group": "5211101",
    "list_icon_type": "member",
    "list_icon_id": "1634161",
    "start_load_voice_id": "302103003",
    "end_load_voice_id": "302100003",
    "banner": "banner_gacha_321111.png",
    "scriptPath": "5211101.txt"
  },
  {
    "id": "5211102",
    "sort_order": "1",
    "title_text": "Mighty Martial Arts Girls & Boys",
    "summary_text": "Rin and Mitsurugi both received outfits made by Aqua herself. But when Mitsurugi discovered Rin received her outfit for free, he finds himself cursing a very familiar name.",
    "gacha_id": "321112",
    "banner_group": "5211102",
    "list_icon_type": "member",
    "list_icon_id": "1134130",
    "start_load_voice_id": "302111002",
    "end_load_voice_id": "302113003",
    "banner": "banner_gacha_321112.png",
    "scriptPath": "5211102.txt"
  },
  {
    "id": "5211103",
    "sort_order": "1",
    "title_text": "OVERLORD Collaboration P2",
    "summary_text": "Megumin was searching for jewelry to match her new outfit, but Shalltear seemed to continue having trouble understanding the Crimson Demon sense of style.",
    "gacha_id": "321113",
    "banner_group": "5211103",
    "list_icon_type": "member",
    "list_icon_id": "1654161",
    "start_load_voice_id": "302102002",
    "end_load_voice_id": "302165002",
    "banner": "banner_gacha_321113.png",
    "scriptPath": "5211103.txt"
  },
  {
    "id": "5211201",
    "sort_order": "1",
    "title_text": "Delivering Happiness Santa Claus",
    "summary_text": "Along with Vanir, Megumin and Yunyun dressed up in Santa costumes to deliver present. And ever-innocent Komekko sees her opportunity, and decided to tell Santa what she wanted that year.",
    "gacha_id": "321121",
    "banner_group": "5211201",
    "list_icon_type": "member",
    "list_icon_id": "1024169",
    "start_load_voice_id": "302106002",
    "end_load_voice_id": "302102002",
    "banner": "banner_gacha_321121.png",
    "scriptPath": "5211201.txt"
  },
  {
    "id": "5211202",
    "sort_order": "1",
    "title_text": "Delivering Happiness Santa Claus",
    "summary_text": "Arue and Iris snuck in and left presents for the dozing Kazuma and Megumin, but discovered an egregious mistake when Kazuma and Megumin were opening their presents the next morning.",
    "gacha_id": "321122",
    "banner_group": "5211202",
    "list_icon_type": "member",
    "list_icon_id": "1074169",
    "start_load_voice_id": "302110002",
    "end_load_voice_id": "302107002",
    "banner": "banner_gacha_321122.png",
    "scriptPath": "5211202.txt"
  },
  {
    "id": "5211203",
    "sort_order": "1",
    "title_text": "Winter Wonderland! Snowfall",
    "summary_text": "Mia and Komekko enjoyed playing in the fresh snow. Lia, watching over the pair for the day, played excitedly with them until their ravenous bellies started grumbling...",
    "gacha_id": "321123",
    "banner_group": "5211203",
    "list_icon_type": "member",
    "list_icon_id": "1144110",
    "start_load_voice_id": "302118003",
    "end_load_voice_id": "302114002",
    "banner": "banner_gacha_321123.png",
    "scriptPath": "5211203.txt"
  },
  {
    "id": "5220101",
    "sort_order": "1",
    "title_text": "Fortunes! New Year's Furisode",
    "summary_text": "Vanir, Wiz, and Yunyun planned a mochi pounding performance in hopes of generating sales for the shop.",
    "gacha_id": "322011",
    "banner_group": "5220101",
    "list_icon_type": "member",
    "list_icon_id": "1054172",
    "start_load_voice_id": "302128002",
    "end_load_voice_id": "302105002",
    "banner": "banner_gacha_322011.png",
    "scriptPath": "5220101.txt"
  },
  {
    "id": "5220102",
    "sort_order": "1",
    "title_text": "Lovely Hot Spring",
    "summary_text": "After an exhausting quest, Mel and Cielo were ready to share a nice, hot bath to relax and rejuvenate, but Mel's prankster spirit came bubbling forth!",
    "gacha_id": "322012",
    "banner_group": "5220102",
    "list_icon_type": "member",
    "list_icon_id": "1154107",
    "start_load_voice_id": "302151002",
    "end_load_voice_id": "302115003",
    "banner": "banner_gacha_322012.png",
    "scriptPath": "5220102.txt"
  },
  {
    "id": "5220103",
    "sort_order": "1",
    "title_text": "Winter Wonderland! Snowfall",
    "summary_text": "With Amy in tow, Cecily was on her way to Samuidoh to recruit people to the Order of Axis. It's freezing, but that's no problem for Cecily, who swore her fiery passion would keep her warm!",
    "gacha_id": "322013",
    "banner_group": "5220103",
    "list_icon_type": "member",
    "list_icon_id": "1094110",
    "start_load_voice_id": "302109003",
    "end_load_voice_id": "302119002",
    "banner": "banner_gacha_322013.png",
    "scriptPath": "5220103.txt"
  },
  {
    "id": "5220201",
    "sort_order": "1",
    "title_text": "Yummy Treats Valentine",
    "summary_text": "Erika, Rin, and Komekko were having a great time making sweets together, but secrets came out as they discussed who they would give them to...",
    "gacha_id": "322021",
    "banner_group": "5220201",
    "list_icon_type": "member",
    "list_icon_id": "1084178",
    "start_load_voice_id": "302116002",
    "end_load_voice_id": "302108002",
    "banner": "banner_gacha_322021.png",
    "scriptPath": "5220201.txt"
  },
  {
    "id": "5220202",
    "sort_order": "1",
    "title_text": "Stylish Transformation! Special Outfit",
    "summary_text": "Wearing their old outfits from their lives in Japan, Lia and Mitsurugi began reflecting on their journey thus far. But both found themselves content in their new lives.",
    "gacha_id": "322022",
    "banner_group": "5220202",
    "list_icon_type": "member",
    "list_icon_id": "1144180",
    "start_load_voice_id": "302114002",
    "end_load_voice_id": "302111002",
    "banner": "banner_gacha_322022.png",
    "scriptPath": "5220202.txt"
  },
  {
    "id": "5220203",
    "sort_order": "1",
    "title_text": "Glamorous Casino Bunny",
    "summary_text": "Melissa, who never takes a bet she won't win, was hesitant when Vanir suggested they visit the casino together. However, the wily demon had a plan to ensure victory.",
    "gacha_id": "322023",
    "banner_group": "5220203",
    "list_icon_type": "member",
    "list_icon_id": "1174114",
    "start_load_voice_id": "302128002",
    "end_load_voice_id": "302117002",
    "banner": "banner_gacha_322023.png",
    "scriptPath": "5220203.txt"
  },
  {
    "id": "5220302",
    "sort_order": "1",
    "title_text": "Lolisa Joins the Battle! Newbie Succubus",
    "summary_text": "The two regulars arrived at the succubus cafe and filled out the papers, but there was still a long time until nightfall.",
    "gacha_id": "322032",
    "banner_group": "5220302",
    "list_icon_type": "member",
    "list_icon_id": "1694100",
    "start_load_voice_id": "302169002",
    "end_load_voice_id": "302169003",
    "banner": "banner_gacha_322032.png",
    "scriptPath": null
  },
  {
    "id": "5220401",
    "sort_order": "1",
    "title_text": "Knight and Thief’s Friendship",
    "summary_text": "Chris, Darkness, and Komekko visit the Eris Church. Darkness tells Komekko an old story.",
    "gacha_id": "322041",
    "banner_group": "5220401",
    "list_icon_type": "member",
    "list_icon_id": "1044183",
    "start_load_voice_id": "302103002",
    "end_load_voice_id": "302104002",
    "banner": "banner_gacha_322041.png",
    "scriptPath": null
  },
  {
    "id": "5220402",
    "sort_order": "1",
    "title_text": "Youthful School Life",
    "summary_text": "Rin and Cielo return from a quest wearing school uniforms. They sense the suspicious looks they are receiving.",
    "gacha_id": "322042",
    "banner_group": "5220402",
    "list_icon_type": "member",
    "list_icon_id": "1134144",
    "start_load_voice_id": "302115002",
    "end_load_voice_id": "302113003",
    "banner": "banner_gacha_322042.png",
    "scriptPath": null
  },
  {
    "id": "5220403",
    "sort_order": "1",
    "title_text": "Roleplaying! Beautiful Opera",
    "summary_text": "Cecily captures a female guest's heart by showing her a play. But there's something fishy about this play….",
    "gacha_id": "322043",
    "banner_group": "5220403",
    "list_icon_type": "member",
    "list_icon_id": "1284116",
    "start_load_voice_id": "302109002",
    "end_load_voice_id": "302128003",
    "banner": "banner_gacha_322043.png",
    "scriptPath": null
  },
  {
    "id": "5220501",
    "sort_order": "1",
    "title_text": "A Certain Scientific Railgun Collaboration",
    "summary_text": "Megumin and Yunyun invite Mikoto and Kurooko to the Crimson Demon Village. They have a great time talking about school.",
    "gacha_id": "322051",
    "banner_group": "5220501",
    "list_icon_type": "member",
    "list_icon_id": "1834189",
    "start_load_voice_id": "302183002",
    "end_load_voice_id": "302184003",
    "banner": "banner_gacha_322051.png",
    "scriptPath": null
  },
  {
    "id": "5220502",
    "sort_order": "1",
    "title_text": "Manic Mansion! Maid",
    "summary_text": "Kazuma is welcomed by the maid and butler upon returning to the mansion. He senses something strange about the two devoted people….",
    "gacha_id": "322052",
    "banner_group": "5220502",
    "list_icon_type": "member",
    "list_icon_id": "1514117",
    "start_load_voice_id": "302112002",
    "end_load_voice_id": "302151002",
    "banner": "banner_gacha_322052.png",
    "scriptPath": null
  },
  {
    "id": "5220503",
    "sort_order": "1",
    "title_text": "A Certain Scientific Railgun Collaboration",
    "summary_text": "Accelerator takes Misaka Sister and Last Order to a restaurant. Kazuma who just happened to be there, joins them…",
    "gacha_id": "322053",
    "banner_group": "5220503",
    "list_icon_type": "member",
    "list_icon_id": "1854189",
    "start_load_voice_id": "302186002",
    "end_load_voice_id": "302185002",
    "banner": "banner_gacha_322053.png",
    "scriptPath": null
  },
  {
    "id": "5220602",
    "sort_order": "1",
    "title_text": "Starry Arabian Nights",
    "summary_text": "Mia and Yunyun are excited after wearing native desert outfits. What does Mia say to Yunyun who is embarrassed because the outfit is too revealing?",
    "gacha_id": "322062",
    "banner_group": "5220602",
    "list_icon_type": "member",
    "list_icon_id": "1064125",
    "start_load_voice_id": "302118002",
    "end_load_voice_id": "302106002",
    "banner": "banner_gacha_322062.png",
    "scriptPath": null
  },
  {
    "id": "5220603",
    "sort_order": "1",
    "title_text": "Lovely Hot Spring",
    "summary_text": "Wiz and Lolisa visit a hot spring after getting some time off. But Wiz's vacation seems to have a purpose.",
    "gacha_id": "322063",
    "banner_group": "5220603",
    "list_icon_type": "member",
    "list_icon_id": "1054107",
    "start_load_voice_id": "302105002",
    "end_load_voice_id": "302169002",
    "banner": "banner_gacha_322063.png",
    "scriptPath": null
  },
  {
    "id": "5220701",
    "sort_order": "1",
    "title_text": "Sunshine Summer Memories",
    "summary_text": "Megumin is in charge of cooking at the beach market. But Megumin's dishes are so bizarre that even Vanir is at a loss for words.",
    "gacha_id": "322071",
    "banner_group": "5220701",
    "list_icon_type": "member",
    "list_icon_id": "1024191",
    "start_load_voice_id": "302102002",
    "end_load_voice_id": "302128002",
    "banner": "banner_gacha_322071.png",
    "scriptPath": null
  },
  {
    "id": "5220702",
    "sort_order": "1",
    "title_text": "Sunshine Summer Memories",
    "summary_text": "Mel and Komekko are enjoying fireworks with Kazuma. The two tomboyish girls seem to enjoy the fireworks in a flashy way as well.",
    "gacha_id": "322072",
    "banner_group": "5220702",
    "list_icon_type": "member",
    "list_icon_id": "1084191",
    "start_load_voice_id": "302108002",
    "end_load_voice_id": "302151002",
    "banner": "banner_gacha_322072.png",
    "scriptPath": null
  },
  {
    "id": "5220703",
    "sort_order": "1",
    "title_text": "Sunshine Summer Memories",
    "summary_text": "Lolisa is tasked with customer service at the beach market. She is eager to impress Vanir, but her usual working habits keep on working against her….",
    "gacha_id": "322073",
    "banner_group": "5220703",
    "list_icon_type": "member",
    "list_icon_id": "1694191",
    "start_load_voice_id": "302169003",
    "end_load_voice_id": "302128002",
    "banner": "banner_gacha_322073.png",
    "scriptPath": null
  },
  {
    "id": "5220801",
    "sort_order": "1",
    "title_text": "<size=30>The Rising of the Shield Hero Season 3 Collaboration</size>",
    "summary_text": "Aqua and Raphtalia's parties get closer by wearing matching outfits. They decide to go eat at the restaurant together...",
    "gacha_id": "322081",
    "banner_group": "5220801",
    "list_icon_type": "member",
    "list_icon_id": "1924195",
    "start_load_voice_id": "302193002",
    "end_load_voice_id": "302193003",
    "banner": "banner_gacha_322081.png",
    "scriptPath": null
  },
  {
    "id": "5220802",
    "sort_order": "1",
    "title_text": "Fireworks at the Yukata Festival",
    "summary_text": "Iris sneaked out on a local festival day with Amy. The food Amy bought from the market was something that Iris had never seen before.",
    "gacha_id": "322082",
    "banner_group": "5220802",
    "list_icon_type": "member",
    "list_icon_id": "1074196",
    "start_load_voice_id": "302107002",
    "end_load_voice_id": "302119002",
    "banner": "banner_gacha_322082.png",
    "scriptPath": null
  },
  {
    "id": "5220803",
    "sort_order": "1",
    "title_text": "Ninja Transformation!",
    "summary_text": "Melissa needs a way to sneak in somewhere, so Kazuma prepared a ninja outfit by Melissa's request... Who will be her next target now?",
    "gacha_id": "322083",
    "banner_group": "5220803",
    "list_icon_type": "member",
    "list_icon_id": "1174127",
    "start_load_voice_id": "302117002",
    "end_load_voice_id": "302117003",
    "banner": "banner_gacha_322083.png",
    "scriptPath": null
  },
  {
    "id": "5220901",
    "sort_order": "1",
    "title_text": "Let's Groove! Explosion Goddess Lalatina",
    "summary_text": "Explosion Goddess Lalatina reunited. One night, Kazuma overhears them talking.",
    "gacha_id": "322091",
    "banner_group": "5220901",
    "list_icon_type": "member",
    "list_icon_id": "1014181",
    "start_load_voice_id": "302101002",
    "end_load_voice_id": "302103003",
    "banner": "banner_gacha_322091.png",
    "scriptPath": null
  },
  {
    "id": "5221001",
    "sort_order": "1",
    "title_text": "Trick or Treat of the Mysterious Night",
    "summary_text": "Arue is interested in the Halloween festival held at Axel. She can't wait for the event to start.",
    "gacha_id": "322101",
    "banner_group": "5221001",
    "list_icon_type": "member",
    "list_icon_id": "1104199",
    "start_load_voice_id": "302110002",
    "end_load_voice_id": "302110003",
    "banner": "banner_gacha_322101.png",
    "scriptPath": null
  },
  {
    "id": "5221002",
    "sort_order": "1",
    "title_text": "Trick or Treat of the Mysterious Night",
    "summary_text": "Lolisa learning Halloween manners from Megumin. But it isn't that easy...",
    "gacha_id": "322102",
    "banner_group": "5221002",
    "list_icon_type": "member",
    "list_icon_id": "1024199",
    "start_load_voice_id": "302102002",
    "end_load_voice_id": "302169003",
    "banner": "banner_gacha_322102.png",
    "scriptPath": null
  },
  {
    "id": "5221101",
    "sort_order": "1",
    "title_text": "Bofuri Collaboration",
    "summary_text": "Maple and her guild members are diligently harvesting cabbages and lettuces. Sally and Kasumi do it easily, but Maple is having a hard time.",
    "gacha_id": "322111",
    "banner_group": "5221101",
    "list_icon_type": "member",
    "list_icon_id": "1954203",
    "start_load_voice_id": "302195002",
    "end_load_voice_id": "302196002",
    "banner": "banner_gacha_322111.png",
    "scriptPath": null
  },
  {
    "id": "5221202",
    "sort_order": "1",
    "title_text": "Happiness Gift! Santa Claus",
    "summary_text": "Komekko takes a closer look at the monster collection. She's seems particularly interested in the reindeer because...?",
    "gacha_id": "322122",
    "banner_group": "5221202",
    "list_icon_type": "member",
    "list_icon_id": "1014207",
    "start_load_voice_id": "302108002",
    "end_load_voice_id": "302101002",
    "banner": "banner_gacha_322122.png",
    "scriptPath": null
  },
  {
    "id": "5221203",
    "sort_order": "1",
    "title_text": "Happiness Gift! Santa Claus",
    "summary_text": "Lolisa came to meet Vanir wearing a cute Santa outfit. She is determined to help him promote his shop.",
    "gacha_id": "322123",
    "banner_group": "5221203",
    "list_icon_type": "member",
    "list_icon_id": "1694207",
    "start_load_voice_id": "302128002",
    "end_load_voice_id": "302169003",
    "banner": "banner_gacha_322123.png",
    "scriptPath": null
  },
  {
    "id": "5230101",
    "sort_order": "1",
    "title_text": "Brilliant! New Year’s Furisode",
    "summary_text": "Yunyun, who is desperately wishing for a “friend” as her New Year’s first prayer, tries to offer everything she has after earing about the offering from Lia.",
    "gacha_id": "323011",
    "banner_group": "5230101",
    "list_icon_type": "member",
    "list_icon_id": "1064208",
    "start_load_voice_id": "302106002",
    "end_load_voice_id": "302114003",
    "banner": "banner_gacha_323011.png",
    "scriptPath": null
  },
  {
    "id": "5230102",
    "sort_order": "1",
    "title_text": "Brilliant! New Year’s Furisode",
    "summary_text": "Kazuma receives a New Year’s Card from Cecily who is enjoying the New Year’s atmosphere. It seems there are a lot of stuff written in the card...",
    "gacha_id": "323012",
    "banner_group": "5230102",
    "list_icon_type": "member",
    "list_icon_id": "1094208",
    "start_load_voice_id": "302109002",
    "end_load_voice_id": "302109003",
    "banner": "banner_gacha_323012.png",
    "scriptPath": null
  },
  {
    "id": "5230103",
    "sort_order": "1",
    "title_text": "Jobless Reincarnation Collaboration",
    "summary_text": "Megumin dresses and poses cool like Roxy. She asks Roxy to introduce herself but as a result...",
    "gacha_id": "323013",
    "banner_group": "5230103",
    "list_icon_type": "member",
    "list_icon_id": "1994210",
    "start_load_voice_id": "302102002",
    "end_load_voice_id": "302199003",
    "banner": "banner_gacha_323013.png",
    "scriptPath": null
  },
  {
    "id": "5230201",
    "sort_order": "1",
    "title_text": "Jobless Reincarnation Collaboration",
    "summary_text": "Eris and Iris go on a quest wearing the same thing. Kazuma and Rudeus joins them just in case...",
    "gacha_id": "323021",
    "banner_group": "5230201",
    "list_icon_type": "member",
    "list_icon_id": "2004210",
    "start_load_voice_id": "302107002",
    "end_load_voice_id": "302200002",
    "banner": "banner_gacha_323021.png",
    "scriptPath": null
  },
  {
    "id": "5230202",
    "sort_order": "1",
    "title_text": "Pit-A-Pat Sweet Valentine",
    "summary_text": "Darkness and Lia tries making chocolate. As a result, the counter top turns into a battlefield...",
    "gacha_id": "323022",
    "banner_group": "5230202",
    "list_icon_type": "member",
    "list_icon_id": "1034211",
    "start_load_voice_id": "302114002",
    "end_load_voice_id": "302103002",
    "banner": "banner_gacha_323022.png",
    "scriptPath": null
  },
  {
    "id": "5230301",
    "sort_order": "1",
    "title_text": "Enjoy the City! TOKYO Coordination",
    "summary_text": "Megumin and Darkness can't hide their amazement after seeing the unfamiliar city of Tokyo. At that moment, someone calls them...",
    "gacha_id": "323031",
    "banner_group": "5230301",
    "list_icon_type": "member",
    "list_icon_id": "1024213",
    "start_load_voice_id": "302103002",
    "end_load_voice_id": "302102002",
    "banner": "banner_gacha_323031.png",
    "scriptPath": null
  },
  {
    "id": "5230302",
    "sort_order": "1",
    "title_text": "Enjoy the City! TOKYO Coordination",
    "summary_text": "On the way to buy some crepe, Aqua and Wiz sees a long line in front of the shop. Aqua gets tired of the line that doesn't seem like it's going to get any shorter...",
    "gacha_id": "323032",
    "banner_group": "5230302",
    "list_icon_type": "member",
    "list_icon_id": "1014213",
    "start_load_voice_id": "302101002",
    "end_load_voice_id": "302105003",
    "banner": "banner_gacha_323032.png",
    "scriptPath": null
  },
  {
    "id": "5230303",
    "sort_order": "1",
    "title_text": "Claire Joins the Battle! The Escort of the Princess",
    "summary_text": "On her day off, Claire is planning to go on a quest with Kazuma's party. After hearing that, Iris says she also wants to join her...",
    "gacha_id": "323033",
    "banner_group": "5230303",
    "list_icon_type": "member",
    "list_icon_id": "1264100",
    "start_load_voice_id": "302126002",
    "end_load_voice_id": "302126003",
    "banner": "banner_gacha_323033.png",
    "scriptPath": null
  },
  {
    "id": "5230401",
    "sort_order": "1",
    "title_text": "Admission! Crimson Magic School",
    "summary_text": "Iris is contemplating if she should wear the Crimson Demon school uniform to the banquet. Even Claire can't admonish since Iris looks so adorable...",
    "gacha_id": "323041",
    "banner_group": "5230401",
    "list_icon_type": "member",
    "list_icon_id": "1074215",
    "start_load_voice_id": "302107002",
    "end_load_voice_id": "302107003",
    "banner": "banner_gacha_323041.png",
    "scriptPath": null
  },
  {
    "id": "5230402",
    "sort_order": "1",
    "title_text": "<size=34>Funifura & Dodonko Joins the Battle! Crimson Demon Classmate</size>",
    "summary_text": "Funifura was practicing her introduction before meeting Kazuma’s party. However, no matter how hard she tries, Dodonko can't memorize her lines...",
    "gacha_id": "323042",
    "banner_group": "5230402",
    "list_icon_type": "member",
    "list_icon_id": "1814100",
    "start_load_voice_id": "302167002",
    "end_load_voice_id": "302168003",
    "banner": "banner_gacha_323042.png",
    "scriptPath": null
  },
  {
    "id": "5230403",
    "sort_order": "1",
    "title_text": "We are Komekko Detectives Club!",
    "summary_text": "Detectives club formed! Komekko and Mia decides to help someone in need. But let’s fill bellies first...!",
    "gacha_id": "323043",
    "banner_group": "5230403",
    "list_icon_type": "member",
    "list_icon_id": "1084217",
    "start_load_voice_id": "302108002",
    "end_load_voice_id": "302108002",
    "banner": "banner_gacha_323043.png",
    "scriptPath": null
  },
  {
    "id": "5230501",
    "sort_order": "1",
    "title_text": "Meow Meow! Cat Ear Miko",
    "summary_text": "Chris and Yunyun still has a hard time adapting to working as a staff in the cat ear tea house. They discover a cute cat when they went outside for a break.",
    "gacha_id": "323051",
    "banner_group": "5230501",
    "list_icon_type": "member",
    "list_icon_id": "1064218",
    "start_load_voice_id": "302104002",
    "end_load_voice_id": "302106002",
    "banner": "banner_gacha_323051.png",
    "scriptPath": null
  },
  {
    "id": "5230502",
    "sort_order": "1",
    "title_text": "We are Komekko Detectives Club!",
    "summary_text": "New Comrade! Komekko gives a cookie to Lolisa who lacks confidence as a member of the detective squad…?",
    "gacha_id": "323052",
    "banner_group": "5230502",
    "list_icon_type": "member",
    "list_icon_id": "1694217",
    "start_load_voice_id": "302169002",
    "end_load_voice_id": "302169003",
    "banner": "banner_gacha_323052.png",
    "scriptPath": null
  },
  {
    "id": "5230503",
    "sort_order": "1",
    "title_text": "<size=34>Re: Zero -Starting Life In Another World! Collaboration</size>",
    "summary_text": "Kazuma met Ram and Beatrice for the first time. In front of the two women who speak harshly, it looks like he is discouraged a bit.",
    "gacha_id": "323053",
    "banner_group": "5230503",
    "list_icon_type": "member",
    "list_icon_id": "2064220",
    "start_load_voice_id": "302207002",
    "end_load_voice_id": "302206002",
    "banner": "banner_gacha_323053.png",
    "scriptPath": null
  },
  {
    "id": "5230601",
    "sort_order": "1",
    "title_text": "<size=34>Re: Zero -Starting Life In Another World! Collaboration</size>",
    "summary_text": "Rem and Emilia wearing the swimsuit prepared by Aqua. With Megumin's suggestion, they decide to play beach volleyball together.",
    "gacha_id": "323061",
    "banner_group": "5230601",
    "list_icon_type": "member",
    "list_icon_id": "1474220",
    "start_load_voice_id": "302147001",
    "end_load_voice_id": "302150001",
    "banner": "banner_gacha_323061.png",
    "scriptPath": null
  },
  {
    "id": "5230602",
    "sort_order": "1",
    "title_text": "Lovely Hot Spring",
    "summary_text": "Iris’s party relaxes at a hot spring. Coincidentally, they start talking about mixed-gender bathing.",
    "gacha_id": "323062",
    "banner_group": "5230602",
    "list_icon_type": "member",
    "list_icon_id": "1074107",
    "start_load_voice_id": "302107002",
    "end_load_voice_id": "302107003",
    "banner": "banner_gacha_323062.png",
    "scriptPath": null
  },
  {
    "id": "5230603",
    "sort_order": "1",
    "title_text": "We are Komekko Detectives Club!",
    "summary_text": "Mia and Yunyun look for something. Mia heads to a skewer shop after catching its scent. Will they be able to find the lost object...?",
    "gacha_id": "323063",
    "banner_group": "5230603",
    "list_icon_type": "member",
    "list_icon_id": "1184217",
    "start_load_voice_id": "302118003",
    "end_load_voice_id": "302106002",
    "banner": "banner_gacha_323063.png",
    "scriptPath": null
  },
  {
    "id": "5230701",
    "sort_order": "1",
    "title_text": "Glowing Night Resort Pool",
    "summary_text": "Darkness and Lolisa have a conversation while taking pictures. Darkness thinks about how her pictures have been released, and falls deep in her own exciting delusion.",
    "gacha_id": "323071",
    "banner_group": "5230701",
    "list_icon_type": "member",
    "list_icon_id": "1034223",
    "start_load_voice_id": "302103002",
    "end_load_voice_id": "302103003",
    "banner": "banner_gacha_323071.png",
    "scriptPath": null
  },
  {
    "id": "5230702",
    "sort_order": "1",
    "title_text": "Glowing Night Resort Pool",
    "summary_text": "Cecily approaches Lia after her performance on stage. Cecily tries everything to make Lia the advertisement model of the Order of Axis.",
    "gacha_id": "323072",
    "banner_group": "5230702",
    "list_icon_type": "member",
    "list_icon_id": "1144223",
    "start_load_voice_id": "302114002",
    "end_load_voice_id": "302114003",
    "banner": "banner_gacha_323074.png",
    "scriptPath": null
  },
  {
    "id": "5230703",
    "sort_order": "1",
    "title_text": "Enjoy! Summer Memories",
    "summary_text": "Kazuma can't take his eyes off of Claire wearing her swimsuit. However, Claire is also looking at someone else.",
    "gacha_id": "323073",
    "banner_group": "5230703",
    "list_icon_type": "member",
    "list_icon_id": "1264223",
    "start_load_voice_id": "302126002",
    "end_load_voice_id": "302126003",
    "banner": "banner_gacha_323073.png",
    "scriptPath": null
  },
  {
    "id": "5230801",
    "sort_order": "1",
    "title_text": "The Melancholy of Haruhi Suzumiya Collaboration",
    "summary_text": "Haruhi becomes delighted after experiencing another world's culture. She bring the unenthusiastic Aqua and Mikuru on a quest.",
    "gacha_id": "323081",
    "banner_group": "5230801",
    "list_icon_type": "member",
    "list_icon_id": "2124225",
    "start_load_voice_id": "302212002",
    "end_load_voice_id": "302101003",
    "banner": "banner_gacha_323081.png",
    "scriptPath": null
  },
  {
    "id": "5230802",
    "sort_order": "1",
    "title_text": "The Melancholy of Haruhi Suzumiya Collaboration",
    "summary_text": "Megumin to Nagato who is quietly reading a book. For some reason, the conversation doesn't seem to go anywhere, but they connected on a deeper level.",
    "gacha_id": "323082",
    "banner_group": "5230802",
    "list_icon_type": "member",
    "list_icon_id": "2134225",
    "start_load_voice_id": "302213002",
    "end_load_voice_id": "302102002",
    "banner": "banner_gacha_323082.png",
    "scriptPath": null
  },
  {
    "id": "5230803",
    "sort_order": "1",
    "title_text": "Get Writing! Great Crimson Writer",
    "summary_text": "You can’t write without a deadline. You eat away at yourself if there is a deadline. Arue is struggling every day while fighting against the deadline.",
    "gacha_id": "323083",
    "banner_group": "5230803",
    "list_icon_type": "member",
    "list_icon_id": "1104226",
    "start_load_voice_id": "302110002",
    "end_load_voice_id": "302110003",
    "banner": "banner_gacha_323083.png",
    "scriptPath": null
  },
  {
    "id": "5230902",
    "sort_order": "1",
    "title_text": "Sprint! Axel Grand Sports Day",
    "summary_text": "Lolisa and Komekko practice hard for the real thing. Megumin and Yunyun start reminiscing while watching the two of them.",
    "gacha_id": "323092",
    "banner_group": "5230902",
    "list_icon_type": "member",
    "list_icon_id": "1694232",
    "start_load_voice_id": "302169002",
    "end_load_voice_id": "302108002",
    "banner": "banner_gacha_323092.png",
    "scriptPath": null
  },
  {
    "id": "5230903",
    "sort_order": "1",
    "title_text": "I’ll cure you! Axel's Angel Squad",
    "summary_text": "Cecily works hard every day to evangelize the Angel Squad’s activities. The other members are barely able to stop Cecily running rampage, let alone do volunteer work.",
    "gacha_id": "323093",
    "banner_group": "5230903",
    "list_icon_type": "member",
    "list_icon_id": "1094229",
    "start_load_voice_id": "302117002",
    "end_load_voice_id": "302109003",
    "banner": "banner_gacha_323093.png",
    "scriptPath": null
  },
  {
    "id": "5900101",
    "sort_order": "1",
    "title_text": "Legendary Adventurer Festival",
    "summary_text": "Busy with their side jobs, the group has forgotten their original mission to defeat the Devil King. Aqua makes them outfits to get them back on track.",
    "gacha_id": "321031",
    "banner_group": "5900100",
    "banner_group_title_text": "Legendary Adventurer Festival",
    "list_icon_type": "member",
    "list_icon_id": "1014142",
    "start_load_voice_id": "302101002",
    "end_load_voice_id": "302103002",
    "banner": "banner_gacha_321035.png",
    "scriptPath": "5900101.txt"
  },
  {
    "id": "5900102",
    "sort_order": "1",
    "title_text": "Legendary Adventurer Festival",
    "summary_text": "Kazuma, garbed in a warrior outfit, is raring to go, as he senses the chance to take down the Devil King and become a legend!",
    "gacha_id": "321061",
    "banner_group": "5900100",
    "banner_group_title_text": "Legendary Adventurer Festival",
    "list_icon_type": "member",
    "list_icon_id": "1004142",
    "start_load_voice_id": "302100002",
    "end_load_voice_id": "302100002",
    "banner": "banner_gacha_321035.png",
    "scriptPath": "5900102.txt"
  },
  {
    "id": "5900103",
    "sort_order": "1",
    "title_text": "Legendary Adventurer Festival",
    "summary_text": "Legendary clothes require a legendary self-introduction—or so says Megumin. However, can Wiz mimic the Crimson Demon way?",
    "gacha_id": "321091",
    "banner_group": "5900100",
    "banner_group_title_text": "Legendary Adventurer Festival",
    "list_icon_type": "member",
    "list_icon_id": "1024142",
    "start_load_voice_id": "302102002",
    "end_load_voice_id": "302105003",
    "banner": "banner_gacha_321035.png",
    "scriptPath": "5900103.txt"
  },
  {
    "id": "5900104",
    "sort_order": "1",
    "title_text": "Legendary Adventurer Festival",
    "summary_text": "Accompanied by Kazuma and company, a fired-up Chris made her way into the ruins in search of legendary treasure, but in a stroke of bad luck, she suffered a direct hit from a certain ability!",
    "gacha_id": "321121",
    "banner_group": "5900100",
    "banner_group_title_text": "Legendary Adventurer Festival",
    "list_icon_type": "member",
    "list_icon_id": "1044142",
    "start_load_voice_id": "302104002",
    "end_load_voice_id": "302104003",
    "banner": "banner_gacha_321035.png",
    "scriptPath": "5900104.txt"
  },
  {
    "id": "5900105",
    "sort_order": "1",
    "title_text": "Legendary Adventurer Festival",
    "summary_text": "Iris and Yunyun wear the Legendary Adventurer outfit. Iris wants to learn something fitting to the awesome outfit…",
    "gacha_id": "322031",
    "banner_group": "5900100",
    "banner_group_title_text": "Legendary Adventurer Festival",
    "list_icon_type": "member",
    "list_icon_id": "1064142",
    "start_load_voice_id": "302107002",
    "end_load_voice_id": "302106002",
    "banner": "banner_gacha_321035.png",
    "scriptPath": null
  },
  {
    "id": "5900106",
    "sort_order": "1",
    "title_text": "Legendary Adventurer Festival",
    "summary_text": "Arue and Cecily obtain the Legendary Adventurer outfit. They talk to each other about their amazing effects…",
    "gacha_id": "322061",
    "banner_group": "5900100",
    "banner_group_title_text": "Legendary Adventurer Festival",
    "list_icon_type": "member",
    "list_icon_id": "1104142",
    "start_load_voice_id": "302110002",
    "end_load_voice_id": "302109002",
    "banner": "banner_gacha_322061.png",
    "scriptPath": null
  },
  {
    "id": "5900107",
    "sort_order": "1",
    "title_text": "Legendary Adventurer Festival",
    "summary_text": "Lia and Cielo try out a new stage outfit. Cielo is worried about Lia who plans to hang her outfit in her room before the performance...",
    "gacha_id": "322091",
    "banner_group": "5900100",
    "banner_group_title_text": "Legendary Adventurer Festival",
    "list_icon_type": "member",
    "list_icon_id": "1144142",
    "start_load_voice_id": "302114002",
    "end_load_voice_id": "302114003",
    "banner": "banner_gacha_322091.png",
    "scriptPath": null
  },
  {
    "id": "5900108",
    "sort_order": "1",
    "title_text": "Legendary Adventurer Festival",
    "summary_text": "The 3 members of Axel Hearts took a photo together for promotion purposes. But Erika doesn't seem to like the photo taken.",
    "gacha_id": "322092",
    "banner_group": "5900100",
    "banner_group_title_text": "Legendary Adventurer Festival",
    "list_icon_type": "member",
    "list_icon_id": "1164142",
    "start_load_voice_id": "302116002",
    "end_load_voice_id": "302116003",
    "banner": "banner_gacha_322092.png",
    "scriptPath": null
  },
  {
    "id": "5900109",
    "sort_order": "1",
    "title_text": "Legendary Adventurer Festival",
    "summary_text": "Dust and Rin try on the equipment they found from the ruin. Then, Dust starts praising Rin's appearance for some reason...",
    "gacha_id": "322121",
    "banner_group": "5900100",
    "banner_group_title_text": "Legendary Adventurer Festival",
    "list_icon_type": "member",
    "list_icon_id": "1124142",
    "start_load_voice_id": "302112002",
    "end_load_voice_id": "302113003",
    "banner": "banner_gacha_322121.png",
    "scriptPath": null
  },
  {
    "id": "5900110",
    "sort_order": "1",
    "title_text": "Legendary Adventurer Festival",
    "summary_text": "Vanir and Lolisa manages Wiz’s shop while wearing the outfit they got from investigating ruins. They are making good sales...",
    "gacha_id": "323031",
    "banner_group": "5900100",
    "banner_group_title_text": "Legendary Adventurer Festival",
    "list_icon_type": "member",
    "list_icon_id": "1284142",
    "start_load_voice_id": "302128003",
    "end_load_voice_id": "302169002",
    "banner": "banner_gacha_321035.png",
    "scriptPath": null
  },
  {
    "id": "5900111",
    "sort_order": "1",
    "title_text": "Legendary Adventurer Festival",
    "summary_text": "Komekko receives a special outfit as a reward for her work as a detective. She tells Megumin that she wants to go on a quest while wearing it but...",
    "gacha_id": "323063",
    "banner_group": "5900100",
    "banner_group_title_text": "Legendary Adventurer Festival",
    "list_icon_type": "member",
    "list_icon_id": "1084142",
    "start_load_voice_id": "302108002",
    "end_load_voice_id": "302108002",
    "banner": "banner_gacha_323063.png",
    "scriptPath": null
  },
  {
    "id": "5900201",
    "sort_order": "1",
    "title_text": "Forbidden Adventurer Festival",
    "summary_text": "Do you want more power… Aqua was delighted to receive the forbidden magic item from Wiz. But it would cost something that Aqua liked very much….",
    "gacha_id": "322101",
    "banner_group": "5900200",
    "banner_group_title_text": "Forbidden Adventurer Festival",
    "list_icon_type": "member",
    "list_icon_id": "1014200",
    "start_load_voice_id": "302101002",
    "end_load_voice_id": "302101003",
    "banner": "banner_gacha_322105.png",
    "scriptPath": null
  },
  {
    "id": "5900202",
    "sort_order": "1",
    "title_text": "Forbidden Adventurer Festival",
    "summary_text": "After wearing the forbidden item, Wiz looks like the Ice Witch. Obviously, the power comes at a cost...",
    "gacha_id": "323011",
    "banner_group": "5900200",
    "banner_group_title_text": "Forbidden Adventurer Festival",
    "list_icon_type": "member",
    "list_icon_id": "1054200",
    "start_load_voice_id": "302105002",
    "end_load_voice_id": "302105003",
    "banner": "banner_gacha_323011.png",
    "scriptPath": null
  },
  {
    "id": "5900203",
    "sort_order": "1",
    "title_text": "Forbidden Adventurer Festival",
    "summary_text": "Megumin, who obtained an incredibly awesome outfit due to an item, fantasizes of her fancy future fanned by her younger sister...?",
    "gacha_id": "323041",
    "banner_group": "5900200",
    "banner_group_title_text": "Forbidden Adventurer Festival",
    "list_icon_type": "member",
    "list_icon_id": "1024200",
    "start_load_voice_id": "302102002",
    "end_load_voice_id": "302108002",
    "banner": "banner_gacha_323041.png",
    "scriptPath": null
  },
  {
    "id": "5900204",
    "sort_order": "1",
    "title_text": "Forbidden Adventurer Festival",
    "summary_text": "After her outfit changes with the power of the Item, Chris’s ability is enhanced. The moment he shackles the guard of the mansion he infiltrated with Bind, an unexpected event occurs.",
    "gacha_id": "323071",
    "banner_group": "5900200",
    "banner_group_title_text": "Forbidden Adventurer Festival",
    "list_icon_type": "member",
    "list_icon_id": "1044200",
    "start_load_voice_id": "302104002",
    "end_load_voice_id": "302104003",
    "banner": "banner_gacha_323071.png",
    "scriptPath": null
  },
  {
    "id": "5900205",
    "sort_order": "1",
    "title_text": "Forbidden Adventurer Festival",
    "summary_text": "Cecily wears a new outfit with the power of an Item. She tries to recruit passersby to join the Order of Axis right away but...?",
    "gacha_id": "324011",
    "banner_group": "5900200",
    "banner_group_title_text": "Forbidden Adventurer Festival",
    "list_icon_type": "member",
    "list_icon_id": "1094200",
    "start_load_voice_id": "302109003",
    "end_load_voice_id": "302109002",
    "banner": "banner_gacha_324011.png",
    "scriptPath": null
  },
  {
    "id": "5900301",
    "sort_order": "1",
    "title_text": "Fantastic Adventurer Festival",
    "summary_text": "Aqua and Darkness who were basically forced to change their appearance. They couldn’t let this go on and discuss a way to return to normal.",
    "gacha_id": "323091",
    "banner_group": "5900300",
    "banner_group_title_text": "Fantastic Adventurer Festival",
    "list_icon_type": "member",
    "list_icon_id": "1014228",
    "start_load_voice_id": "302101003",
    "end_load_voice_id": "302103003",
    "banner": "banner_gacha_323094.png",
    "scriptPath": null
  }
]